{
  "configs": [
    "global.xml",
    "error-handler.xml",
    "hellomule-secureproperties.xml"
  ],
  "secureProperties": [
    "secure.key"
  ],
  "redeploymentEnabled": true,
  "name": "com.mycompany:hellomule-secureproperties:1.0.0-SNAPSHOT",
  "minMuleVersion": "4.4.0",
  "requiredProduct": "MULE_EE",
  "classLoaderModelLoaderDescriptor": {
    "id": "mule",
    "attributes": {
      "exportedPackages": [],
      "exportedResources": [
        "log4j2.xml",
        "global.xml",
        "error-handler.xml",
        "env/local/local.secure.properties",
        "env/local/local.properties",
        "env/dev/dev.properties",
        "env/dev/dev.secure.properties",
        "hellomule-secureproperties.xml"
      ]
    }
  },
  "bundleDescriptorLoader": {
    "id": "mule",
    "attributes": {}
  }
}